odoo/addons/shopinvader_search_engine/README.rst
odoo/addons/shopinvader_search_engine/__init__.py
odoo/addons/shopinvader_search_engine/__manifest__.py
odoo/addons/shopinvader_search_engine/i18n/shopinvader_search_engine.pot
odoo/addons/shopinvader_search_engine/models/__init__.py
odoo/addons/shopinvader_search_engine/models/product_category.py
odoo/addons/shopinvader_search_engine/models/product_product.py
odoo/addons/shopinvader_search_engine/models/product_template.py
odoo/addons/shopinvader_search_engine/models/se_index.py
odoo/addons/shopinvader_search_engine/models/se_indexable_record.py
odoo/addons/shopinvader_search_engine/readme/CONFIGURATION.rst
odoo/addons/shopinvader_search_engine/readme/CONTRIBUTORS.rst
odoo/addons/shopinvader_search_engine/readme/CREDITS.rst
odoo/addons/shopinvader_search_engine/readme/DESCRIPTION.rst
odoo/addons/shopinvader_search_engine/readme/HISTORY.rst
odoo/addons/shopinvader_search_engine/readme/ROADMAP.rst
odoo/addons/shopinvader_search_engine/readme/USAGE.rst
odoo/addons/shopinvader_search_engine/readme/newsfragments/.gitignore
odoo/addons/shopinvader_search_engine/schemas/__init__.py
odoo/addons/shopinvader_search_engine/schemas/category.py
odoo/addons/shopinvader_search_engine/static/description/index.html
odoo/addons/shopinvader_search_engine/tests/__init__.py
odoo/addons/shopinvader_search_engine/tests/common.py
odoo/addons/shopinvader_search_engine/tests/test_category_binding.py
odoo/addons/shopinvader_search_engine/tests/test_product_binding.py
odoo/addons/shopinvader_search_engine/tools/__init__.py
odoo/addons/shopinvader_search_engine/tools/category_serializer.py
odoo/addons/shopinvader_search_engine/tools/product_serializer.py
odoo_addon_shopinvader_search_engine-16.0.1.0.7.dist-info/METADATA
odoo_addon_shopinvader_search_engine-16.0.1.0.7.dist-info/WHEEL
odoo_addon_shopinvader_search_engine-16.0.1.0.7.dist-info/top_level.txt
odoo_addon_shopinvader_search_engine-16.0.1.0.7.dist-info/RECORD
