Metadata-Version: 2.1
Name: odoo-addon-shopinvader_search_engine
Version: 16.0.1.0.7
Summary: Shopinvader Catalog Search Engine Connector
Home-page: https://github.com/shopinvader/odoo-shopinvader
Author: Akretion
License: AGPL-3
Classifier: Programming Language :: Python
Classifier: Framework :: Odoo
Classifier: Framework :: Odoo :: 16.0
Classifier: License :: OSI Approved :: GNU Affero General Public License v3
Classifier: Development Status :: 3 - Alpha
Requires-Python: >=3.10
Requires-Dist: odoo-addon-search-engine-serializer-pydantic<16.1dev,>=16.0dev
Requires-Dist: odoo-addon-shopinvader-product<16.1dev,>=16.0dev
Requires-Dist: odoo<16.1dev,>=16.0a
